stmetrics/__init__.py
stmetrics/__main__.py
stmetrics/basics.py
stmetrics/fractal.py
stmetrics/metrics.py
stmetrics/phenometrics.py
stmetrics/polar.py
stmetrics/utils.py
tsmetrics/__init__.py
tsmetrics/__main__.py
tsmetrics/basics.py
tsmetrics/fractal.py
tsmetrics/metrics.py
tsmetrics/phenometrics.py
tsmetrics/polar.py
tsmetrics/utils.py
stmetrics-0.1.4.dist-info/LICENSE
stmetrics-0.1.4.dist-info/METADATA
stmetrics-0.1.4.dist-info/WHEEL
stmetrics-0.1.4.dist-info/top_level.txt
stmetrics-0.1.4.dist-info/RECORD
