Metadata-Version: 2.1
Name: stmetrics
Version: 0.1.4
Summary: A package to compute metrics from Satellite Image Time Series (SITS).
Home-page: https://github.com/andersonreisoares/stmetrics/
Author: Anderson Soares, Thales Körting
Author-email: andersonreis.geo@gmail.com
License: UNKNOWN
Platform: UNKNOWN
Classifier: Programming Language :: Python :: 3
Classifier: License :: OSI Approved :: MIT License
Classifier: Operating System :: OS Independent
Classifier: Development Status :: 2 - Pre-Alpha
Requires-Dist: scipy
Requires-Dist: sklearn
Requires-Dist: pandas
Requires-Dist: numpy
Requires-Dist: matplotlib
Requires-Dist: shapely
Requires-Dist: descartes
Requires-Dist: nolds
